TSGEngine/__init__.py
TSGEngine/Core/__init__.py
TSGEngine/Core/Component.py
TSGEngine/Core/Math.py
TSGEngine/Core/Scene.py
TSGEngine/Core/Settings.py
TSGEngine/Input/__init__.py
TSGEngine/Input/Input_handler.py
TSGEngine/Input/Key_map
TSGEngine/Logger.py
TSGEngine/Main.py
TSGEngine/Object/__init__.py
TSGEngine/Object/components/Mesh.py
TSGEngine/Object/components/Transform.py
TSGEngine/Object/entity/__init__.py
TSGEngine/Object/entity/Circle.py
TSGEngine/Object/entity/Rectangle.py
TSGEngine/Object/systems/Renderer.py
TSGEngine/Object/systems/Transform_handler.py
TSGEngine/Physics/__init__.py
TSGEngine/Physics/Components/Collider.py
TSGEngine/Physics/Components/Colliders/BallCollider.py
TSGEngine/Physics/Components/Colliders/RectangleCollider.py
TSGEngine/Physics/Components/RigidBody.py
TSGEngine/Physics/Systems/Collision.py
TSGEngine/Physics/Systems/RigidBody.py
TSGEngine/Rendering/__init__.py
TSGEngine/Rendering/OpenGL/Mesh.py
TSGEngine/Rendering/OpenGL/Renderer.py
TSGEngine/Rendering/OpenGL/Shader.py
TSGEngine/Rendering/OpenGL/Texture.py
TSGEngine/Rendering/Vulkan/Mesh.py
TSGEngine/Rendering/Vulkan/Renderer.py
TSGEngine/Rendering/Vulkan/Shader.py
TSGEngine/Rendering/Vulkan/Texture.py
TSGEngine/Shaders/__init__.py
TSGEngine/Shaders/Shader_handler.py
TSGEngine/Texture/__init__.py
TSGEngine/Texture/Texture_handler.py
TSGEngine/Utility/__init__.py
TSGEngine/Utility/Destructible_Class.py
TSGEngine/Utility/Singleton.py
TSGEngine/Window/__init__.py
TSGEngine/Window/GLFW.py
TSGEngine/World/__init__.py
TSGEngine/World/Components/__init__.py
TSGEngine/World/Components/Mesh.py
TSGEngine/World/Components/Transform.py
TSGEngine/World/Entity/__init__.py
TSGEngine/World/Entity/Entity.py
TSGEngine/World/Systems/__init__.py
TSGEngine/World/Systems/BaseSystem.py
TSGEngine/World/Systems/Render_system.py
TSGEngine/World/World.py
tsgengine-0.1.0.dist-info/METADATA
tsgengine-0.1.0.dist-info/WHEEL
tsgengine-0.1.0.dist-info/RECORD
