Metadata-Version: 2.1
Name: tsgengine
Version: 0.1.0
Summary: Too Scrappy Game Engine
License: MIT
Author: Trololoxa221
Author-email: nikolai.2006-2015@yandex.ru
Requires-Python: >=3.9,<4.0
Classifier: License :: OSI Approved :: MIT License
Classifier: Programming Language :: Python :: 3
Classifier: Programming Language :: Python :: 3.9
Classifier: Programming Language :: Python :: 3.10
Classifier: Programming Language :: Python :: 3.11
Requires-Dist: PyOpenGL (>=3.1.7,<4.0.0)
Requires-Dist: PyOpenGL-accelerate (>=3.1.7,<4.0.0)
Requires-Dist: glfw (>=2.6.2,<3.0.0)
Requires-Dist: imgui (>=2.0.0,<3.0.0)
Requires-Dist: numpy (>=1.25.1,<2.0.0)
